fp_addition.v
module fp_addition(
	input clk,	// clock
	input start,	// start signal to begin operation
	input [31:0] fp_input, // 32-bit floating point input 
	
	output [31:0] fp_sum,	// final floating point result
	output reg done,	// operation complete flag
	output reg overflow,	// exponent overflow flag
	output reg underflow	// exponent underflow flag
);

	//-------------------------- FSM States ------------------------
	parameter IDLE = 3'd0,
		  LOAD_B = 3'd1,
		  ALIGN = 3'd2,
		  ADD = 3'd3,
		  NORMALIZE = 3'd4,
		  CHECK = 3'd5,
		  DONE = 3'd6;

	//--------------------------- REGISTER -------------------------
	// 23 bit fraction + 1 hidden bit + extra bits for alignment 
	reg [25:0] frac_a;	// fraction of component A
	reg [25:0] frac_b;	// fraction of component B

	reg [7:0] exp_a;	// exponent of component A
	reg [7:0] exp_b;	// exponent of component B

	reg sign_a;		// sign of component A
	reg sign_b;		// sign of component B
	

	// -------------------------- WIRES ---------------------------
	wire frac_overflow;	// fraction overflow (after addition)
	wire frac_underflow;	// fraction underflow or normalization required

	// used for substraction when sign is negative (2's complement) 
	wire [27:0] frac_a_comp;	
	wire [27:0] frac_b_comp;

	wire [27:0] add_out;	// output of fraction adder

	wire [27:0] frac_sum;	// final fraction after normalization
	
	// ------------------------ Control ----------------------------
	reg [2:0] state;	// FSM state register
	



	// Initial block
	initial
	begin
		state = IDLE;
		done = 0;
		overflow = 0;
		underflow = 0;
		frac_a = 0;
		frac_b = 0;
		exp_a = 0;
		exp_b = 0;
		sign_a = 0;
		sign_b = 0;
	end
	

	// 2's complement (if negative)
	assign frac_a_comp = (sign_a == 1'b1) ? ~({2'b00, frac_a}) + 1 : {2'b00, frac_a}; 
	assign frac_b_comp = (sign_b == 1'b1) ? ~({2'b00, frac_b}) + 1 : {2'b00, frac_b};
	
	// Add
	assign add_out = frac_a_comp + frac_b_comp;	
	
	// back to magnitude
	assign frac_sum = (add_out[27] == 1'b0) ? add_out : (~add_out + 1);
	
	// overflow or underflow detect
	assign frac_overflow = frac_sum[26];
	assign frac_underflow = ~frac_a[25];

	// pack final result
	assign fp_sum = {sign_a, exp_a, frac_a[24:2]};


	// -------------------------------------- FSM -----------------------
	always @(posedge clk)
	begin	
		case(state)
		    IDLE: begin
				if(start == 1'b1)
				begin
					exp_a <= fp_input[30:23];
					sign_a <= fp_input[31];
					frac_a[24:0] <= {fp_input[22:0], 2'b00};
					
					// hidden bit: 0 for zero/denormal, 1 for normal
					frac_a[25] <= (fp_input[30:23] != 8'b0) ? 1'b1 : 1'b0;
					done <= 1'b0;
					overflow <= 1'b0;
					underflow <= 1'b0;
					state <= LOAD_B;
				end
				else
				begin
					state <= IDLE;
				end
			   end	   
		   LOAD_B: begin
				exp_b <= fp_input[30:23];
				sign_b <= fp_input[31];
				frac_b[24:0] <= {fp_input[22:0], 2'b00};
				
				frac_b[25] <= (fp_input[30:23] != 8'b0) ? 1'b1 : 1'b0;
				state <= ALIGN;
			   end
		    ALIGN: begin
				if(frac_a == 0 || frac_b == 0)
				begin
					if(frac_a == 0)
					begin
						frac_a <= frac_b;
						exp_a <= exp_b;
						sign_a <= sign_b;
					end
					state <= ADD;
				end
				else
				begin
					if(exp_a == exp_b)
					begin
						state <= ADD;
					end
					else if(exp_a < exp_b)
					begin
						frac_a <= {1'b0, frac_a[25:1]};
						exp_a <= exp_a + 1;
					end
					else
					begin
						frac_b <= {1'b0, frac_b[25:1]};
						exp_b <= exp_b + 1;
					end
				end
			   end
		      ADD: begin
				sign_a <= add_out[27];
				if(frac_overflow == 1'b0)
				begin

					frac_a <= frac_sum[25:0];
				end
				else
				begin
					frac_a <= frac_sum[26:1];
					exp_a <= exp_a + 1;	
				end
				state <= NORMALIZE;
			   end
		NORMALIZE: begin
			   	if(frac_a == 0)
				begin
					exp_a <= 8'b0000_0000;
					state <= DONE;
				end
				else
				begin
					state <= CHECK;
				end
			   end
		    CHECK: begin
				if(exp_a == 0)
				begin
					underflow <= 1'b1;
					state <= DONE;
				end
				else if (frac_a[25] == 1'b1)
				begin
					state <= DONE;
				end
				else
				begin
					frac_a <= {frac_a[24:0], 1'b0};
					exp_a <= exp_a - 1;
				end
			   end
		     DONE: begin
			 	if(exp_a == 8'hFF)
				begin
					overflow <= 1'b1;
				end
				done <= 1'b1;
				state <= IDLE;	
			   end
		  default: begin
				state <= IDLE;
		  	   end
		endcase
	end
endmodule

tb_fp.v
module tb_fp_addition();
	
	reg clk;
        reg start;
	reg [31:0] fp_input;

	wire [31:0] fp_sum;
	wire done;
	wire overflow;
	wire underflow;

	// design module instantiation
	fp_addition dut(.clk(clk), .start(start), .fp_input(fp_input), .fp_sum(fp_sum), .done(done), .overflow(overflow), .underflow(underflow));
	
	// clock generation
	always #5 clk = ~clk;
        
	// task to print values in modified hex format
	task print_hex;
		input [31:0] val;
		begin
			$write("x%0H%0H%0H%0H_%0H%0H%0H%0H", val[31:28], val[27:24], val[23:20], val[19:16], val[15:12], val[11:8], val[7:4], val[3:0]);
		end
	endtask
	
	// task to apply 2 inputs
	task apply_test;
		input [31:0] a;
		input [31:0] b;
		begin
			@(negedge clk)
			start = 1;
			fp_input = a;
			
			@(negedge clk)
			fp_input = b;

			@(negedge clk)
			start = 0;
			
			wait(done == 1'b1);
			$write("A = "); print_hex(a);
			$write(" | B = "); print_hex(b);
			$write(" | SUM = "); print_hex(fp_sum);
			$display(" | OVERFLOW = %b | UNDERFLOW = %b", overflow, underflow);
			
			#20;
		end
	endtask


	// Test cases
	initial
	begin
		clk = 0;
		start = 0;
		fp_input = 0;

		#12;

		// 0 + 0 
		apply_test(32'h0000_0000, 32'h0000_0000);
			
		// 1.0 + 1.0 = 2.0
		apply_test(32'h3F80_0000, 32'h3F80_0000);

		// -1.0 + -1.0 = -2.0 
		apply_test(32'hBF80_0000, 32'hBF80_0000);
		
		// 1 + -1 = 0
		apply_test(32'h3F80_0000, 32'hBF80_0000);
		
		// max_float + 1
		apply_test(32'h7F7F_FFFF, 32'h3F80_0000);
		
		// -max + -1 
		apply_test(32'hFF7F_FFFF, 32'hBF00_0000);
		
		// max + max -> overflow 
		apply_test(32'h7F7F_FFFF, 32'h7F7F_FFFF);
		
		// -max + -max -> overflow 
		apply_test(32'hFF7F_FFFF, 32'hFF7F_FFFF);
		
		// 1.11x2^8 + -1.11x2^6
		apply_test(32'h43E0_0000, 32'hC2E0_0000);
		
		// -1.11x2^8 + 1.11x2^6
		apply_test(32'hC3E0_0000, 32'h42E0_0000);	
		
		// 1.11x2^127 + 1.11x2^6
		apply_test(32'h7F7F_FFFF, 32'h7380_0000);	

		// -1.11x2^127 + -0.11x2^127
		apply_test(32'hFF7F_FFFF, 32'hF380_0000);
		
		// 1.11x2^127 + 0.11x2^127
		apply_test(32'h7F7F_FFFE, 32'h7380_0000);
		
		// -1.11x2^127 + -0.11x2^127
		apply_test(32'hFF7F_FFFE, 32'hF380_0000);
		
		// 1.1x2^-126 + -1.0x2^-126
		apply_test(32'h00C0_0000, 32'h8080_0000);

		#100;
	       	$finish();
	end

	initial
	begin
		$dumpfile("dump.vcd");
		$dumpvars(0);
	end
endmodule

dump.vcd
$date
	Fri Apr 10 00:34:13 2026
$end
$version
	Icarus Verilog
$end
$timescale
	1s
$end
$scope module tb_fp_addition $end
$var wire 1 ! underflow $end
$var wire 1 " overflow $end
$var wire 32 # fp_sum [31:0] $end
$var wire 1 $ done $end
$var reg 1 % clk $end
$var reg 32 & fp_input [31:0] $end
$var reg 1 ' start $end
$scope module dut $end
$var wire 1 % clk $end
$var wire 32 ( fp_input [31:0] $end
$var wire 1 ) frac_underflow $end
$var wire 1 ' start $end
$var wire 28 * frac_sum [27:0] $end
$var wire 1 + frac_overflow $end
$var wire 28 , frac_b_comp [27:0] $end
$var wire 28 - frac_a_comp [27:0] $end
$var wire 32 . fp_sum [31:0] $end
$var wire 28 / add_out [27:0] $end
$var parameter 3 0 ADD $end
$var parameter 3 1 ALIGN $end
$var parameter 3 2 CHECK $end
$var parameter 3 3 DONE $end
$var parameter 3 4 IDLE $end
$var parameter 3 5 LOAD_B $end
$var parameter 3 6 NORMALIZE $end
$var reg 1 $ done $end
$var reg 8 7 exp_a [7:0] $end
$var reg 8 8 exp_b [7:0] $end
$var reg 26 9 frac_a [25:0] $end
$var reg 26 : frac_b [25:0] $end
$var reg 1 " overflow $end
$var reg 1 ; sign_a $end
$var reg 1 < sign_b $end
$var reg 3 = state [2:0] $end
$var reg 1 ! underflow $end
$upscope $end
$scope task apply_test $end
$var reg 32 > a [31:0] $end
$var reg 32 ? b [31:0] $end
$upscope $end
$scope task print_hex $end
$var reg 32 @ val [31:0] $end
$upscope $end
$upscope $end
$enddefinitions $end
$comment Show the parameter values. $end
$dumpall
b100 6
b1 5
b0 4
b110 3
b101 2
b10 1
b11 0
$end
#0
$dumpvars
bx @
bx ?
bx >
b0 =
0<
0;
b0 :
b0 9
b0 8
b0 7
b0 /
b0 .
b0 -
b0 ,
0+
b0 *
1)
b0 (
0'
b0 &
0%
0$
b0 #
0"
0!
$end
#5
1%
#10
0%
#12
b0 ?
b0 >
#15
1%
#20
1'
0%
#25
b1 =
1%
#30
0%
#35
b10 =
1%
#40
0'
0%
#45
b11 =
1%
#50
0%
#55
b100 =
1%
#60
0%
#65
b110 =
1%
#70
0%
#75
b0 @
b0 =
1$
1%
#80
0%
#85
1%
#90
0%
#95
1%
b111111100000000000000000000000 ?
b111111100000000000000000000000 >
#100
b111111100000000000000000000000 &
b111111100000000000000000000000 (
1'
0%
#105
b10000000000000000000000000 *
0)
b10000000000000000000000000 /
b10000000000000000000000000 -
b1 =
0$
b10000000000000000000000000 9
b111111100000000000000000000000 #
b111111100000000000000000000000 .
b1111111 7
1%
#110
0%
#115
1+
b100000000000000000000000000 *
b100000000000000000000000000 /
b10000000000000000000000000 ,
b10 =
b10000000000000000000000000 :
b1111111 8
1%
#120
0'
0%
#125
b11 =
1%
#130
0%
#135
b100 =
b1000000000000000000000000000000 #
b1000000000000000000000000000000 .
b10000000 7
1%
#140
0%
#145
b101 =
1%
#150
0%
#155
b110 =
1%
#160
0%
#165
b1000000000000000000000000000000 @
b0 =
1$
1%
#170
0%
#175
1%
#180
0%
#185
1%
b10111111100000000000000000000000 ?
b10111111100000000000000000000000 >
#190
b10111111100000000000000000000000 &
b10111111100000000000000000000000 (
1'
0%
#195
0+
b0 *
b0 /
b1110000000000000000000000000 -
b1 =
0$
1;
b10111111100000000000000000000000 #
b10111111100000000000000000000000 .
b1111111 7
1%
#200
0%
#205
1+
b100000000000000000000000000 *
b1100000000000000000000000000 /
b1110000000000000000000000000 ,
b10 =
1<
1%
#210
0'
0%
#215
b11 =
1%
#220
0%
#225
b100 =
b11000000000000000000000000000000 #
b11000000000000000000000000000000 .
b10000000 7
1%
#230
0%
#235
b101 =
1%
#240
0%
#245
b110 =
1%
#250
0%
#255
b11000000000000000000000000000000 @
b0 =
1$
1%
#260
0%
#265
1%
#270
0%
#275
1%
b111111100000000000000000000000 >
#280
b111111100000000000000000000000 &
b111111100000000000000000000000 (
1'
0%
#285
0+
b0 *
b0 /
b10000000000000000000000000 -
b1 =
0$
0;
b111111100000000000000000000000 #
b111111100000000000000000000000 .
b1111111 7
1%
#290
b10111111100000000000000000000000 &
b10111111100000000000000000000000 (
0%
#295
b10 =
1%
#300
0'
0%
#305
b11 =
1%
#310
0%
#315
0+
b10000000000000000000000000 *
1)
b1110000000000000000000000000 /
b0 -
b100 =
b0 9
1%
#320
0%
#325
b110 =
b0 #
b0 .
b0 7
1%
#330
0%
#335
b0 @
b0 =
1$
1%
#340
0%
#345
1%
#350
0%
#355
1%
b111111100000000000000000000000 ?
b1111111011111111111111111111111 >
#360
b1111111011111111111111111111111 &
b1111111011111111111111111111111 (
1'
0%
#365
0+
b1111111111111111111111100 *
0)
b1111111111111111111111100 /
b11111111111111111111111100 -
b1 =
0$
b11111111111111111111111100 9
b1111111011111111111111111111111 #
b1111111011111111111111111111111 .
b11111110 7
1%
#370
b111111100000000000000000000000 &
b111111100000000000000000000000 (
0%
#375
1+
b101111111111111111111111100 *
b101111111111111111111111100 /
b10000000000000000000000000 ,
b10 =
0<
1%
#380
0'
0%
#385
b100111111111111111111111100 *
b100111111111111111111111100 /
b1000000000000000000000000 ,
b10000000 8
b1000000000000000000000000 :
1%
#390
0%
#395
b100011111111111111111111100 *
b100011111111111111111111100 /
b100000000000000000000000 ,
b10000001 8
b100000000000000000000000 :
1%
#400
0%
#405
b100001111111111111111111100 *
b100001111111111111111111100 /
b10000000000000000000000 ,
b10000010 8
b10000000000000000000000 :
1%
#410
0%
#415
b100000111111111111111111100 *
b100000111111111111111111100 /
b1000000000000000000000 ,
b10000011 8
b1000000000000000000000 :
1%
#420
0%
#425
b100000011111111111111111100 *
b100000011111111111111111100 /
b100000000000000000000 ,
b10000100 8
b100000000000000000000 :
1%
#430
0%
#435
b100000001111111111111111100 *
b100000001111111111111111100 /
b10000000000000000000 ,
b10000101 8
b10000000000000000000 :
1%
#440
0%
#445
b100000000111111111111111100 *
b100000000111111111111111100 /
b1000000000000000000 ,
b10000110 8
b1000000000000000000 :
1%
#450
0%
#455
b100000000011111111111111100 *
b100000000011111111111111100 /
b100000000000000000 ,
b10000111 8
b100000000000000000 :
1%
#460
0%
#465
b100000000001111111111111100 *
b100000000001111111111111100 /
b10000000000000000 ,
b10001000 8
b10000000000000000 :
1%
#470
0%
#475
b100000000000111111111111100 *
b100000000000111111111111100 /
b1000000000000000 ,
b10001001 8
b1000000000000000 :
1%
#480
0%
#485
b100000000000011111111111100 *
b100000000000011111111111100 /
b100000000000000 ,
b10001010 8
b100000000000000 :
1%
#490
0%
#495
b100000000000001111111111100 *
b100000000000001111111111100 /
b10000000000000 ,
b10001011 8
b10000000000000 :
1%
#500
0%
#505
b100000000000000111111111100 *
b100000000000000111111111100 /
b1000000000000 ,
b10001100 8
b1000000000000 :
1%
#510
0%
#515
b100000000000000011111111100 *
b100000000000000011111111100 /
b100000000000 ,
b10001101 8
b100000000000 :
1%
#520
0%
#525
b100000000000000001111111100 *
b100000000000000001111111100 /
b10000000000 ,
b10001110 8
b10000000000 :
1%
#530
0%
#535
b100000000000000000111111100 *
b100000000000000000111111100 /
b1000000000 ,
b10001111 8
b1000000000 :
1%
#540
0%
#545
b100000000000000000011111100 *
b100000000000000000011111100 /
b100000000 ,
b10010000 8
b100000000 :
1%
#550
0%
#555
b100000000000000000001111100 *
b100000000000000000001111100 /
b10000000 ,
b10010001 8
b10000000 :
1%
#560
0%
#565
b100000000000000000000111100 *
b100000000000000000000111100 /
b1000000 ,
b10010010 8
b1000000 :
1%
#570
0%
#575
b100000000000000000000011100 *
b100000000000000000000011100 /
b100000 ,
b10010011 8
b100000 :
1%
#580
0%
#585
b100000000000000000000001100 *
b100000000000000000000001100 /
b10000 ,
b10010100 8
b10000 :
1%
#590
0%
#595
b100000000000000000000000100 *
b100000000000000000000000100 /
b1000 ,
b10010101 8
b1000 :
1%
#600
0%
#605
b100000000000000000000000000 *
b100000000000000000000000000 /
b100 ,
b10010110 8
b100 :
1%
#610
0%
#615
0+
b11111111111111111111111110 *
b11111111111111111111111110 /
b10 ,
b10010111 8
b10 :
1%
#620
0%
#625
b11111111111111111111111101 *
b11111111111111111111111101 /
b1 ,
b10011000 8
b1 :
1%
#630
0%
#635
b11111111111111111111111100 *
b11111111111111111111111100 /
b0 ,
b10011001 8
b0 :
1%
#640
0%
#645
b11 =
1%
#650
0%
#655
b100 =
1%
#660
0%
#665
b101 =
1%
#670
0%
#675
b110 =
1%
#680
0%
#685
b1111111011111111111111111111111 @
b0 =
1$
1%
#690
0%
#695
1%
#700
0%
#705
1%
b10111111000000000000000000000000 ?
b11111111011111111111111111111111 >
#710
b11111111011111111111111111111111 &
b11111111011111111111111111111111 (
1'
0%
#715
0+
b11111111111111111111111100 *
b1100000000000000000000000100 /
b1100000000000000000000000100 -
b1 =
0$
b11111111011111111111111111111111 #
b11111111011111111111111111111111 .
1;
1%
#720
b10111111000000000000000000000000 &
b10111111000000000000000000000000 (
0%
#725
1+
b101111111111111111111111100 *
b1010000000000000000000000100 /
b1110000000000000000000000000 ,
b10 =
b10000000000000000000000000 :
1<
b1111110 8
1%
#730
0'
0%
#735
b100111111111111111111111100 *
b1011000000000000000000000100 /
b1111000000000000000000000000 ,
b1111111 8
b1000000000000000000000000 :
1%
#740
0%
#745
b100011111111111111111111100 *
b1011100000000000000000000100 /
b1111100000000000000000000000 ,
b10000000 8
b100000000000000000000000 :
1%
#750
0%
#755
b100001111111111111111111100 *
b1011110000000000000000000100 /
b1111110000000000000000000000 ,
b10000001 8
b10000000000000000000000 :
1%
#760
0%
#765
b100000111111111111111111100 *
b1011111000000000000000000100 /
b1111111000000000000000000000 ,
b10000010 8
b1000000000000000000000 :
1%
#770
0%
#775
b100000011111111111111111100 *
b1011111100000000000000000100 /
b1111111100000000000000000000 ,
b10000011 8
b100000000000000000000 :
1%
#780
0%
#785
b100000001111111111111111100 *
b1011111110000000000000000100 /
b1111111110000000000000000000 ,
b10000100 8
b10000000000000000000 :
1%
#790
0%
#795
b100000000111111111111111100 *
b1011111111000000000000000100 /
b1111111111000000000000000000 ,
b10000101 8
b1000000000000000000 :
1%
#800
0%
#805
b100000000011111111111111100 *
b1011111111100000000000000100 /
b1111111111100000000000000000 ,
b10000110 8
b100000000000000000 :
1%
#810
0%
#815
b100000000001111111111111100 *
b1011111111110000000000000100 /
b1111111111110000000000000000 ,
b10000111 8
b10000000000000000 :
1%
#820
0%
#825
b100000000000111111111111100 *
b1011111111111000000000000100 /
b1111111111111000000000000000 ,
b10001000 8
b1000000000000000 :
1%
#830
0%
#835
b100000000000011111111111100 *
b1011111111111100000000000100 /
b1111111111111100000000000000 ,
b10001001 8
b100000000000000 :
1%
#840
0%
#845
b100000000000001111111111100 *
b1011111111111110000000000100 /
b1111111111111110000000000000 ,
b10001010 8
b10000000000000 :
1%
#850
0%
#855
b100000000000000111111111100 *
b1011111111111111000000000100 /
b1111111111111111000000000000 ,
b10001011 8
b1000000000000 :
1%
#860
0%
#865
b100000000000000011111111100 *
b1011111111111111100000000100 /
b1111111111111111100000000000 ,
b10001100 8
b100000000000 :
1%
#870
0%
#875
b100000000000000001111111100 *
b1011111111111111110000000100 /
b1111111111111111110000000000 ,
b10001101 8
b10000000000 :
1%
#880
0%
#885
b100000000000000000111111100 *
b1011111111111111111000000100 /
b1111111111111111111000000000 ,
b10001110 8
b1000000000 :
1%
#890
0%
#895
b100000000000000000011111100 *
b1011111111111111111100000100 /
b1111111111111111111100000000 ,
b10001111 8
b100000000 :
1%
#900
0%
#905
b100000000000000000001111100 *
b1011111111111111111110000100 /
b1111111111111111111110000000 ,
b10010000 8
b10000000 :
1%
#910
0%
#915
b100000000000000000000111100 *
b1011111111111111111111000100 /
b1111111111111111111111000000 ,
b10010001 8
b1000000 :
1%
#920
0%
#925
b100000000000000000000011100 *
b1011111111111111111111100100 /
b1111111111111111111111100000 ,
b10010010 8
b100000 :
1%
#930
0%
#935
b100000000000000000000001100 *
b1011111111111111111111110100 /
b1111111111111111111111110000 ,
b10010011 8
b10000 :
1%
#940
0%
#945
b100000000000000000000000100 *
b1011111111111111111111111100 /
b1111111111111111111111111000 ,
b10010100 8
b1000 :
1%
#950
0%
#955
b100000000000000000000000000 *
b1100000000000000000000000000 /
b1111111111111111111111111100 ,
b10010101 8
b100 :
1%
#960
0%
#965
0+
b11111111111111111111111110 *
b1100000000000000000000000010 /
b1111111111111111111111111110 ,
b10010110 8
b10 :
1%
#970
0%
#975
b11111111111111111111111101 *
b1100000000000000000000000011 /
b1111111111111111111111111111 ,
b10010111 8
b1 :
1%
#980
0%
#985
b11111111111111111111111100 *
b1100000000000000000000000100 /
b0 ,
b10011000 8
b0 :
1%
#990
0%
#995
b11 =
1%
#1000
0%
#1005
b100 =
1%
#1010
0%
#1015
b101 =
1%
#1020
0%
#1025
b110 =
1%
#1030
0%
#1035
b11111111011111111111111111111111 @
b0 =
1$
1%
#1040
0%
#1045
1%
#1050
0%
#1055
1%
b1111111011111111111111111111111 ?
b1111111011111111111111111111111 >
#1060
b1111111011111111111111111111111 &
b1111111011111111111111111111111 (
1'
0%
#1065
0+
b11111111111111111111111100 *
b11111111111111111111111100 /
b11111111111111111111111100 -
b1 =
0$
b1111111011111111111111111111111 #
b1111111011111111111111111111111 .
0;
1%
#1070
0%
#1075
1+
b111111111111111111111111000 *
b111111111111111111111111000 /
b11111111111111111111111100 ,
b10 =
b11111111111111111111111100 :
0<
b11111110 8
1%
#1080
0'
0%
#1085
b11 =
1%
#1090
0%
#1095
b100 =
b1111111111111111111111111111111 #
b1111111111111111111111111111111 .
b11111111 7
1%
#1100
0%
#1105
b101 =
1%
#1110
0%
#1115
b110 =
1%
#1120
0%
#1125
b1111111111111111111111111111111 @
b0 =
1$
1"
1%
#1130
0%
#1135
1%
#1140
0%
#1145
1%
b11111111011111111111111111111111 ?
b11111111011111111111111111111111 >
#1150
b11111111011111111111111111111111 &
b11111111011111111111111111111111 (
1'
0%
#1155
0+
b0 *
b0 /
b1100000000000000000000000100 -
b1 =
0"
0$
1;
b11111111011111111111111111111111 #
b11111111011111111111111111111111 .
b11111110 7
1%
#1160
0%
#1165
1+
b111111111111111111111111000 *
b1000000000000000000000001000 /
b1100000000000000000000000100 ,
b10 =
1<
1%
#1170
0'
0%
#1175
b11 =
1%
#1180
0%
#1185
b100 =
b11111111111111111111111111111111 #
b11111111111111111111111111111111 .
b11111111 7
1%
#1190
0%
#1195
b101 =
1%
#1200
0%
#1205
b110 =
1%
#1210
0%
#1215
b11111111111111111111111111111111 @
b0 =
1$
1"
1%
#1220
0%
#1225
1%
#1230
0%
#1235
1%
b11000010111000000000000000000000 ?
b1000011111000000000000000000000 >
#1240
b1000011111000000000000000000000 &
b1000011111000000000000000000000 (
1'
0%
#1245
0+
b11111111111111111111100 *
b1111100000000000000000000100 /
b11100000000000000000000000 -
b1 =
0"
0$
b11100000000000000000000000 9
0;
b1000011111000000000000000000000 #
b1000011111000000000000000000000 .
b10000111 7
1%
#1250
b11000010111000000000000000000000 &
b11000010111000000000000000000000 (
0%
#1255
b0 *
b0 /
b1100100000000000000000000000 ,
b10 =
b11100000000000000000000000 :
b10000101 8
1%
#1260
0'
0%
#1265
b1110000000000000000000000 *
b1110000000000000000000000 /
b1110010000000000000000000000 ,
b10000110 8
b1110000000000000000000000 :
1%
#1270
0%
#1275
b10101000000000000000000000 *
b10101000000000000000000000 /
b1111001000000000000000000000 ,
b10000111 8
b111000000000000000000000 :
1%
#1280
0%
#1285
b11 =
1%
#1290
0%
#1295
b1110000000000000000000000 *
b1110000000000000000000000 /
b10101000000000000000000000 -
b1000011101010000000000000000000 #
b1000011101010000000000000000000 .
b100 =
b10101000000000000000000000 9
1%
#1300
0%
#1305
b101 =
1%
#1310
0%
#1315
b110 =
1%
#1320
0%
#1325
b1000011101010000000000000000000 @
b0 =
1$
1%
#1330
0%
#1335
1%
#1340
0%
#1345
1%
b1000010111000000000000000000000 ?
b11000011111000000000000000000000 >
#1350
b11000011111000000000000000000000 &
b11000011111000000000000000000000 (
1'
0%
#1355
1+
b100011000000000000000000000 *
b1011101000000000000000000000 /
b1100100000000000000000000000 -
b1 =
0$
b11100000000000000000000000 9
b11000011111000000000000000000000 #
b11000011111000000000000000000000 .
1;
1%
#1360
b1000010111000000000000000000000 &
b1000010111000000000000000000000 (
0%
#1365
0+
b0 *
b0 /
b11100000000000000000000000 ,
b10 =
b11100000000000000000000000 :
0<
b10000101 8
1%
#1370
0'
0%
#1375
0+
b1110000000000000000000000 *
b1110010000000000000000000000 /
b1110000000000000000000000 ,
b10000110 8
b1110000000000000000000000 :
1%
#1380
0%
#1385
b10101000000000000000000000 *
b1101011000000000000000000000 /
b111000000000000000000000 ,
b10000111 8
b111000000000000000000000 :
1%
#1390
0%
#1395
b11 =
1%
#1400
0%
#1405
b1110000000000000000000000 *
b1110010000000000000000000000 /
b1101011000000000000000000000 -
b11000011101010000000000000000000 #
b11000011101010000000000000000000 .
b100 =
b10101000000000000000000000 9
1%
#1410
0%
#1415
b101 =
1%
#1420
0%
#1425
b110 =
1%
#1430
0%
#1435
b11000011101010000000000000000000 @
b0 =
1$
1%
#1440
0%
#1445
1%
#1450
0%
#1455
1%
b1110011100000000000000000000000 ?
b1111111011111111111111111111111 >
#1460
b1111111011111111111111111111111 &
b1111111011111111111111111111111 (
1'
0%
#1465
1+
b100110111111111111111111100 *
b100110111111111111111111100 /
b11111111111111111111111100 -
b1 =
0$
b11111111111111111111111100 9
0;
b1111111011111111111111111111111 #
b1111111011111111111111111111111 .
b11111110 7
1%
#1470
b1110011100000000000000000000000 &
b1110011100000000000000000000000 (
0%
#1475
b101111111111111111111111100 *
b101111111111111111111111100 /
b10000000000000000000000000 ,
b10 =
b10000000000000000000000000 :
b11100111 8
1%
#1480
0'
0%
#1485
b100111111111111111111111100 *
b100111111111111111111111100 /
b1000000000000000000000000 ,
b11101000 8
b1000000000000000000000000 :
1%
#1490
0%
#1495
b100011111111111111111111100 *
b100011111111111111111111100 /
b100000000000000000000000 ,
b11101001 8
b100000000000000000000000 :
1%
#1500
0%
#1505
b100001111111111111111111100 *
b100001111111111111111111100 /
b10000000000000000000000 ,
b11101010 8
b10000000000000000000000 :
1%
#1510
0%
#1515
b100000111111111111111111100 *
b100000111111111111111111100 /
b1000000000000000000000 ,
b11101011 8
b1000000000000000000000 :
1%
#1520
0%
#1525
b100000011111111111111111100 *
b100000011111111111111111100 /
b100000000000000000000 ,
b11101100 8
b100000000000000000000 :
1%
#1530
0%
#1535
b100000001111111111111111100 *
b100000001111111111111111100 /
b10000000000000000000 ,
b11101101 8
b10000000000000000000 :
1%
#1540
0%
#1545
b100000000111111111111111100 *
b100000000111111111111111100 /
b1000000000000000000 ,
b11101110 8
b1000000000000000000 :
1%
#1550
0%
#1555
b100000000011111111111111100 *
b100000000011111111111111100 /
b100000000000000000 ,
b11101111 8
b100000000000000000 :
1%
#1560
0%
#1565
b100000000001111111111111100 *
b100000000001111111111111100 /
b10000000000000000 ,
b11110000 8
b10000000000000000 :
1%
#1570
0%
#1575
b100000000000111111111111100 *
b100000000000111111111111100 /
b1000000000000000 ,
b11110001 8
b1000000000000000 :
1%
#1580
0%
#1585
b100000000000011111111111100 *
b100000000000011111111111100 /
b100000000000000 ,
b11110010 8
b100000000000000 :
1%
#1590
0%
#1595
b100000000000001111111111100 *
b100000000000001111111111100 /
b10000000000000 ,
b11110011 8
b10000000000000 :
1%
#1600
0%
#1605
b100000000000000111111111100 *
b100000000000000111111111100 /
b1000000000000 ,
b11110100 8
b1000000000000 :
1%
#1610
0%
#1615
b100000000000000011111111100 *
b100000000000000011111111100 /
b100000000000 ,
b11110101 8
b100000000000 :
1%
#1620
0%
#1625
b100000000000000001111111100 *
b100000000000000001111111100 /
b10000000000 ,
b11110110 8
b10000000000 :
1%
#1630
0%
#1635
b100000000000000000111111100 *
b100000000000000000111111100 /
b1000000000 ,
b11110111 8
b1000000000 :
1%
#1640
0%
#1645
b100000000000000000011111100 *
b100000000000000000011111100 /
b100000000 ,
b11111000 8
b100000000 :
1%
#1650
0%
#1655
b100000000000000000001111100 *
b100000000000000000001111100 /
b10000000 ,
b11111001 8
b10000000 :
1%
#1660
0%
#1665
b100000000000000000000111100 *
b100000000000000000000111100 /
b1000000 ,
b11111010 8
b1000000 :
1%
#1670
0%
#1675
b100000000000000000000011100 *
b100000000000000000000011100 /
b100000 ,
b11111011 8
b100000 :
1%
#1680
0%
#1685
b100000000000000000000001100 *
b100000000000000000000001100 /
b10000 ,
b11111100 8
b10000 :
1%
#1690
0%
#1695
b100000000000000000000000100 *
b100000000000000000000000100 /
b1000 ,
b11111101 8
b1000 :
1%
#1700
0%
#1705
b100000000000000000000000000 *
b100000000000000000000000000 /
b100 ,
b11111110 8
b100 :
1%
#1710
0%
#1715
b11 =
1%
#1720
0%
#1725
0+
b10000000000000000000000100 *
b10000000000000000000000100 /
b10000000000000000000000000 -
b100 =
b1111111100000000000000000000000 #
b1111111100000000000000000000000 .
b11111111 7
b10000000000000000000000000 9
1%
#1730
0%
#1735
b101 =
1%
#1740
0%
#1745
b110 =
1%
#1750
0%
#1755
b1111111100000000000000000000000 @
b0 =
1$
1"
1%
#1760
0%
#1765
1%
#1770
0%
#1775
1%
b11110011100000000000000000000000 ?
b11111111011111111111111111111111 >
#1780
b11111111011111111111111111111111 &
b11111111011111111111111111111111 (
1'
0%
#1785
0+
b11111111111111111111111000 *
b1100000000000000000000001000 /
b1100000000000000000000000100 -
b1 =
0"
0$
b11111111111111111111111100 9
1;
b11111111011111111111111111111111 #
b11111111011111111111111111111111 .
b11111110 7
1%
#1790
b11110011100000000000000000000000 &
b11110011100000000000000000000000 (
0%
#1795
1+
b101111111111111111111111100 *
b1010000000000000000000000100 /
b1110000000000000000000000000 ,
b10 =
b10000000000000000000000000 :
1<
b11100111 8
1%
#1800
0'
0%
#1805
b100111111111111111111111100 *
b1011000000000000000000000100 /
b1111000000000000000000000000 ,
b11101000 8
b1000000000000000000000000 :
1%
#1810
0%
#1815
b100011111111111111111111100 *
b1011100000000000000000000100 /
b1111100000000000000000000000 ,
b11101001 8
b100000000000000000000000 :
1%
#1820
0%
#1825
b100001111111111111111111100 *
b1011110000000000000000000100 /
b1111110000000000000000000000 ,
b11101010 8
b10000000000000000000000 :
1%
#1830
0%
#1835
b100000111111111111111111100 *
b1011111000000000000000000100 /
b1111111000000000000000000000 ,
b11101011 8
b1000000000000000000000 :
1%
#1840
0%
#1845
b100000011111111111111111100 *
b1011111100000000000000000100 /
b1111111100000000000000000000 ,
b11101100 8
b100000000000000000000 :
1%
#1850
0%
