fp.v
module fp_addition(
	input clk,	// clock
	input start,	// start signal to begin operation
	input [31:0] fp_input, // 32-bit floating point input 
	
	output [31:0] fp_sum,	// final floating point result
	output reg done,	// operation complete flag
	output reg overflow,	// exponent overflow flag
	output reg underflow	// exponent underflow flag
);

	//-------------------------- FSM States ------------------------
	parameter IDLE = 3'd0,
		  LOAD_B = 3'd1,
		  ALIGN = 3'd2,
		  ADD = 3'd3,
		  NORMALIZE = 3'd4,
		  CHECK = 3'd5,
		  DONE = 3'd6;

	//--------------------------- REGISTER -------------------------
	reg [25:0] frac_a;	// fraction of component A
				/* 23 bit fraction + 1 hidden bit + extra bits for alignment*/ 
	reg [25:0] frac_b;	// fraction of component B

	reg [7:0] exp_a;	// exponent of component A
	reg [7:0] exp_b;	// exponent of component B

	reg sign_a;		// sign of component A
	reg sign_b;		// sign of component B
	

	// -------------------------- WIRES ---------------------------
	wire frac_overflow;	// fraction overflow (after addition)
	wire frac_underflow;	// fraction underflow or normalization required

	wire [27:0] fraction_a_comp;	// used for substraction when sign is negative (2's complement) 
	wire [27:0] fraction_b_comp;

	wire [27:0] add_out;	// output of fraction adder

	wire [27:0] frac_sum;	// final fraction after normalization
	
	// ------------------------ Control ----------------------------
	reg [2:0] state;	// FSM state register
	



	// Initial block
	initial
	begin
		state = IDLE;
		done = 0;
		overflow = 0;
		underflow = 0;
		frac_a = 0;
		frac_b = 0;
		exp_a = 0;
		exp_b = 0;
		sign_a = 0;
		sign_b = 0;
	end
	

	// 2's complement (if negative)
	assign frac_a_comp = (sign_a == 1'b1) ? ~({2'b00, frac_a}) + 1 : {2'b00, frac_a}; 
	assign frac_b_comp = (sign_b == 1'b1) ? ~({2'b00, frac_b}) + 1 : {2'b00, frac_b};
	
	// Add
	assign add_out = (frac_a_comp + frac_a_comp);	
	
	// back to magnitude
	assign frac_sum = (add_out[27] == 1'b0) ? add_out : ~add_out + 1;
	
	// overflow or underflow detect
	assign frac_overflow = frac_sum[27] ^ frac_sum[26];
	assign frac_underflow = ~frac_a[25];

	// pack final result
	assign fp_sum = {sign_a, exp_a, frac_a[24:2]};


	// -------------------------------------- FSM -----------------------
	always @(posedge clk)
	begin	
		case(state)
		    IDLE: begin
				if(start == 1'b1)
				begin
					exp_a <= fp_input[30:23];
					sign_a <= fp_input[31];
					frac_a[24:0] <= {fp_input[22:0], 2'b00};
					if(fp_input == 0)
					begin
						frac_b[25] <= 1'b0;
					end	
					else
					begin
						frac_b[25] <= 1'b1;
					end
					done <= 1'b0;
					overflow <= 1'b0;
					underflow <= 1'b0;
					state <= 1;
				end
				else
				begin
					state <= IDLE;
				end
			   end	   
		   LOAD_B: begin
				exp_b <= fp_input[30:23];
				sign_b <= fp_input[31];
				frac_b[24:0] <= {fp_input[22:0], 2'b00};
				if(fp_input == 0)
				begin
					frac_b[25] <= 1'b0;
				end	
				else
				begin
					frac_b[25] <= 1'b1;
				end
				state <= ALIGN;
			   end
		    ALIGN: begin
				if(frac_a == 0 | frac_b == 0)
				begin
					state <= ADD;
				end
				else
				begin
					if(exp_a == exp_b)
					begin
						state <= ADD;
					end
					else if(exp_a < exp_b)
					begin
						frac_a <= {1'b0, frac_a[25:1]};
						exp_a <= exp_a + 1;
					end
					else
					begin
						frac_b <= {1'b0, frac_b[25:1]};
						exp_b <= exp_b + 1;
					end
				end
			   end
		      ADD: begin
				sign_a <= add_out[27];
				if(frac_overflow == 1'b0)
				begin
					frac_a <= frac_sum[25:0];
				end
				else
				begin
					frac_a <= frac_sum[26:1];
					exp_a <= exp_a + 1;
				end
				state <= NORMALIZE;
			   end
		NORMALIZE: begin
			   	if(frac_a == 0)
				begin
					exp_a <= 8'b0000_0000;
					state <= DONE;
				end
				else
				begin
					state <= CHECK;
				end
			   end
		    CHECK: begin
				if(exp_a == 0)
				begin
					underflow <= 1'b1;
					state <= DONE;
				end
				else if (frac_overflow == 1'b0)
				begin
					state <= DONE;
				end
				else
				begin
					frac_a <= {frac_a[24:0], 1'b0};
					exp_a <= exp_a - 1;
				end
			   end
		     DONE: begin
			 	if(exp_a == 255)
				begin
					overflow <= 1'b1;
				end
				done <= 1'b1;
				state <= 0;	
			   end
		  default: begin
				state <= IDLE;
		  	   end
		endcase
	end
endmodule

tb_fp.v
module tb_fp_addition();
	
	reg clk;
        reg start;
	reg [31:0] fp_input;

	wire [31:0] fp_sum;
	wire done;
	wire overflow;
	wire underflow;

	// design module instantiation
	fp_addition dut(.clk(clk), .start(start), .fp_input(fp_input), .fp_sum(fp_sum), .done(done), .overflow(overflow), .underflow(underflow));
	
	// clock generation
	always #5 clk = ~clk;

	// task to apply 2 inputs
	task apply_test;
		input [31:0] a;
		input [31:0] b;
		begin
			@(posedge clk)
			start = 1;
			fp_input = a;

			@(posedge clk)
			fp_input = b;

			@(posedge clk)
			start = 0;

			wait(done);
			$display("A = %h | B = %h | SUM = %h | OVF = %b | UNF = %b", a, b, fp_sum, overflow, underflow);
			
			#10;
		end
	endtask


	// Test cases
	initial
	begin
		clk = 0;
		start = 0;

		#10
		// 0 + 0 
		apply_test(32'h0000_0000, 32'h0000_0000);
		 
		// 1 + 1
		apply_test(32'h3F80_0000, 32'h3F80_0000);

		// -1 + -1 
		apply_test(32'hBF80_0000, 32'hBF80_0000);
		
		// 1 + -1
		apply_test(32'h3F80_0000, 32'hBF80_0000);
		
		// max + 1
		apply_test(32'h7F7F_FFFF, 32'h3F80_0000);
		
		// -max + -1 
		apply_test(32'hFF7F_FFFF, 32'hBF00_0000);
		
		// max + max -> overflow 
		apply_test(32'h7F7F_FFFF, 32'h7F7F_FFFF);
		
		// -max + -max -> overflow 
		apply_test(32'hFF7F_FFFF, 32'hFF7F_FFFF);
		
		// 1.11x2^8 + -1.11x2^6
		apply_test(32'h43E0_0000, 32'hC2E0_0000);
		
		// -1.11x2^8 + 1.11x2^6
		apply_test(32'hCE30_0000, 32'h42E0_0000);	
		
		// 1.11x2^127 + 1.11x2^6
		apply_test(32'h7F7F_FFFF, 32'h7380_0000);	

		// -1.11x2^127 + -0.11x2^127
		apply_test(32'hFF7F_FFFF, 32'hF380_0000);
		
		// 1.11x2^127 + 0.11x2^127
		apply_test(32'h7F7F_FFFE, 32'h7380_0000);
		
		// -1.11x2^127 + -0.11x2^127
		apply_test(32'hFF7F_FFFE, 32'hF380_0000);
		
		// 1.1x2^-126 + -1.0x2^-126
		apply_test(32'h00C0_0000, 32'h8080_0000);

		#10 $finish();
	end
endmodule

dump.vcd
$date
	Thu Apr  9 00:43:55 2026
$end
$version
	Icarus Verilog
$end
$timescale
	1s
$end
$scope module tb_fp_addition $end
$var wire 1 ! underflow $end
$var wire 1 " overflow $end
$var wire 32 # fp_sum [31:0] $end
$var wire 1 $ done $end
$var reg 1 % clk $end
$var reg 32 & fp_input [31:0] $end
$var reg 1 ' start $end
$scope module dut $end
$var wire 1 % clk $end
$var wire 32 ( fp_input [31:0] $end
$var wire 1 ) frac_overflow $end
$var wire 1 * frac_underflow $end
$var wire 1 ' start $end
$var wire 28 + frac_sum [27:0] $end
$var wire 1 , frac_b_comp $end
$var wire 1 - frac_a_comp $end
$var wire 32 . fp_sum [31:0] $end
$var wire 28 / add_out [27:0] $end
$var parameter 3 0 ADD $end
$var parameter 3 1 ALIGN $end
$var parameter 3 2 CHECK $end
$var parameter 3 3 DONE $end
$var parameter 3 4 IDLE $end
$var parameter 3 5 LOAD_B $end
$var parameter 3 6 NORMALIZE $end
$var reg 1 $ done $end
$var reg 8 7 exp_a [7:0] $end
$var reg 8 8 exp_b [7:0] $end
$var reg 26 9 frac_a [25:0] $end
$var reg 26 : frac_b [25:0] $end
$var reg 1 " overflow $end
$var reg 1 ; sign_a $end
$var reg 1 < sign_b $end
$var reg 3 = state [2:0] $end
$var reg 1 ! underflow $end
$upscope $end
$scope task apply_test $end
$var reg 32 > a [31:0] $end
$var reg 32 ? b [31:0] $end
$upscope $end
$upscope $end
$enddefinitions $end
$comment Show the parameter values. $end
$dumpall
b100 6
b1 5
b0 4
b110 3
b101 2
b10 1
b11 0
$end
#0
$dumpvars
bx ?
bx >
b0 =
0<
0;
b0 :
b0 9
b0 8
b0 7
b0 /
b0 .
0-
0,
b0 +
1*
0)
bx (
0'
bx &
0%
0$
b0 #
0"
0!
$end
#5
1%
#10
0%
b0 ?
b0 >
#15
b1 =
b0 &
b0 (
1'
1%
#20
0%
#25
b10 =
1%
#30
0%
#35
b11 =
0'
1%
#40
0%
#45
b100 =
1%
#50
0%
#55
b110 =
1%
#60
0%
#65
b0 =
1$
1%
#70
0%
#75
0*
b1 =
0$
b10000000000000000000000000 9
b111111100000000000000000000000 #
b111111100000000000000000000000 .
b1111111 7
b111111100000000000000000000000 &
b111111100000000000000000000000 (
1'
1%
b111111100000000000000000000000 ?
b111111100000000000000000000000 >
#80
0%
#85
b10 =
b10000000000000000000000000 :
b1111111 8
1%
#90
0%
#95
b11 =
0'
1%
#100
0%
#105
1*
b100 =
b0 9
1%
#110
0%
#115
b110 =
b0 #
b0 .
b0 7
1%
#120
0%
#125
b0 =
1$
1%
#130
0%
#135
0*
b1 =
0$
b10000000000000000000000000 9
1;
b10111111100000000000000000000000 #
b10111111100000000000000000000000 .
b1111111 7
b10111111100000000000000000000000 &
b10111111100000000000000000000000 (
1'
1%
b10111111100000000000000000000000 ?
b10111111100000000000000000000000 >
#140
0%
#145
b10 =
1<
1%
#150
0%
#155
b11 =
0'
1%
#160
0%
#165
1*
b100 =
b0 9
b111111100000000000000000000000 #
b111111100000000000000000000000 .
0;
1%
#170
0%
#175
b110 =
b0 #
b0 .
b0 7
1%
#180
0%
#185
b0 =
1$
1%
#190
0%
#195
0*
b1 =
0$
b10000000000000000000000000 9
b111111100000000000000000000000 #
b111111100000000000000000000000 .
b1111111 7
b111111100000000000000000000000 &
b111111100000000000000000000000 (
1'
1%
b111111100000000000000000000000 >
#200
0%
#205
b10 =
0<
b10111111100000000000000000000000 &
b10111111100000000000000000000000 (
1%
#210
0%
#215
b11 =
0'
1%
#220
0%
#225
1*
b100 =
b0 9
1%
#230
0%
#235
b110 =
b0 #
b0 .
b0 7
1%
#240
0%
#245
b0 =
1$
1%
#250
0%
#255
0*
b1 =
0$
b11111111111111111111111100 9
b1111111011111111111111111111111 #
b1111111011111111111111111111111 .
b11111110 7
b1111111011111111111111111111111 &
b1111111011111111111111111111111 (
1'
1%
b111111100000000000000000000000 ?
b1111111011111111111111111111111 >
#260
0%
#265
b10 =
b11111111111111111111111100 :
b11111110 8
b111111100000000000000000000000 &
b111111100000000000000000000000 (
1%
#270
0%
#275
b11 =
0'
1%
#280
0%
#285
1*
b1111111000000000000000000000000 #
b1111111000000000000000000000000 .
b100 =
b0 9
1%
#290
0%
#295
b110 =
b0 #
b0 .
b0 7
1%
#300
0%
#305
b0 =
1$
1%
#310
0%
#315
0*
b1 =
0$
b11111111111111111111111100 9
1;
b11111111011111111111111111111111 #
b11111111011111111111111111111111 .
b11111110 7
b11111111011111111111111111111111 &
b11111111011111111111111111111111 (
1'
1%
b10111111000000000000000000000000 ?
b11111111011111111111111111111111 >
#320
0%
#325
b10 =
1<
b10111111000000000000000000000000 &
b10111111000000000000000000000000 (
1%
#330
0%
#335
b11 =
0'
1%
#340
0%
#345
1*
b100 =
b0 9
b1111111000000000000000000000000 #
b1111111000000000000000000000000 .
0;
1%
#350
0%
#355
b110 =
b0 #
b0 .
b0 7
1%
#360
0%
#365
b0 =
1$
1%
#370
0%
#375
0*
b1 =
0$
b11111111111111111111111100 9
b1111111011111111111111111111111 #
b1111111011111111111111111111111 .
b11111110 7
b1111111011111111111111111111111 &
b1111111011111111111111111111111 (
1'
1%
b1111111011111111111111111111111 ?
b1111111011111111111111111111111 >
#380
0%
#385
b10 =
0<
1%
#390
0%
#395
b11 =
0'
1%
#400
0%
#405
1*
b1111111000000000000000000000000 #
b1111111000000000000000000000000 .
b100 =
b0 9
1%
#410
0%
#415
b110 =
b0 #
b0 .
b0 7
1%
#420
0%
#425
b0 =
1$
1%
#430
0%
#435
0*
b1 =
0$
b11111111111111111111111100 9
1;
b11111111011111111111111111111111 #
b11111111011111111111111111111111 .
b11111110 7
b11111111011111111111111111111111 &
b11111111011111111111111111111111 (
1'
1%
b11111111011111111111111111111111 ?
b11111111011111111111111111111111 >
#440
0%
#445
b10 =
1<
1%
#450
0%
#455
b11 =
0'
1%
#460
0%
#465
1*
b100 =
b0 9
b1111111000000000000000000000000 #
b1111111000000000000000000000000 .
0;
1%
#470
0%
#475
b110 =
b0 #
b0 .
b0 7
1%
#480
0%
#485
b0 =
1$
1%
#490
0%
#495
0*
b1 =
0$
b11100000000000000000000000 9
b1000011111000000000000000000000 #
b1000011111000000000000000000000 .
b10000111 7
b1000011111000000000000000000000 &
b1000011111000000000000000000000 (
1'
1%
b11000010111000000000000000000000 ?
b1000011111000000000000000000000 >
#500
0%
#505
b10 =
b11100000000000000000000000 :
0<
b10000111 8
b11000010111000000000000000000000 &
b11000010111000000000000000000000 (
1%
#510
0%
#515
b11 =
0'
1%
#520
0%
#525
1*
b1000011100000000000000000000000 #
b1000011100000000000000000000000 .
b100 =
b0 9
1%
#530
0%
#535
b110 =
b0 #
b0 .
b0 7
1%
#540
0%
#545
b0 =
1$
1%
#550
0%
#555
0*
b1 =
0$
b10110000000000000000000000 9
1;
b11001110001100000000000000000000 #
b11001110001100000000000000000000 .
b10011100 7
b11001110001100000000000000000000 &
b11001110001100000000000000000000 (
1'
1%
b1000010111000000000000000000000 ?
b11001110001100000000000000000000 >
#560
0%
#565
b10 =
b10110000000000000000000000 :
1<
b10011100 8
b1000010111000000000000000000000 &
b1000010111000000000000000000000 (
1%
#570
0%
#575
b11 =
0'
1%
#580
0%
#585
1*
b100 =
b0 9
b1001110000000000000000000000000 #
b1001110000000000000000000000000 .
0;
1%
#590
0%
#595
b110 =
b0 #
b0 .
b0 7
1%
#600
0%
#605
b0 =
1$
1%
#610
0%
#615
0*
b1 =
0$
b11111111111111111111111100 9
b1111111011111111111111111111111 #
b1111111011111111111111111111111 .
b11111110 7
b1111111011111111111111111111111 &
b1111111011111111111111111111111 (
1'
1%
b1110011100000000000000000000000 ?
b1111111011111111111111111111111 >
#620
0%
#625
b10 =
b11111111111111111111111100 :
0<
b11111110 8
b1110011100000000000000000000000 &
b1110011100000000000000000000000 (
1%
#630
0%
#635
b11 =
0'
1%
#640
0%
#645
1*
b1111111000000000000000000000000 #
b1111111000000000000000000000000 .
b100 =
b0 9
1%
#650
0%
#655
b110 =
b0 #
b0 .
b0 7
1%
#660
0%
#665
b0 =
1$
1%
#670
0%
#675
0*
b1 =
0$
b11111111111111111111111100 9
1;
b11111111011111111111111111111111 #
b11111111011111111111111111111111 .
b11111110 7
b11111111011111111111111111111111 &
b11111111011111111111111111111111 (
1'
1%
b11110011100000000000000000000000 ?
b11111111011111111111111111111111 >
#680
0%
#685
b10 =
1<
b11110011100000000000000000000000 &
b11110011100000000000000000000000 (
1%
#690
0%
#695
b11 =
0'
1%
#700
0%
#705
1*
b100 =
b0 9
b1111111000000000000000000000000 #
b1111111000000000000000000000000 .
0;
1%
#710
0%
#715
b110 =
b0 #
b0 .
b0 7
1%
#720
0%
#725
b0 =
1$
1%
#730
0%
#735
0*
b1 =
0$
b11111111111111111111111000 9
b1111111011111111111111111111110 #
b1111111011111111111111111111110 .
b11111110 7
b1111111011111111111111111111110 &
b1111111011111111111111111111110 (
1'
1%
b1110011100000000000000000000000 ?
b1111111011111111111111111111110 >
#740
0%
#745
b10 =
b11111111111111111111111000 :
0<
b1110011100000000000000000000000 &
b1110011100000000000000000000000 (
1%
#750
0%
#755
b11 =
0'
1%
#760
0%
#765
1*
b1111111000000000000000000000000 #
b1111111000000000000000000000000 .
b100 =
b0 9
1%
#770
0%
#775
b110 =
b0 #
b0 .
b0 7
1%
#780
0%
#785
b0 =
1$
1%
#790
0%
#795
0*
b1 =
0$
b11111111111111111111111000 9
1;
b11111111011111111111111111111110 #
b11111111011111111111111111111110 .
b11111110 7
b11111111011111111111111111111110 &
b11111111011111111111111111111110 (
1'
1%
b11110011100000000000000000000000 ?
b11111111011111111111111111111110 >
#800
0%
#805
b10 =
1<
b11110011100000000000000000000000 &
b11110011100000000000000000000000 (
1%
#810
0%
#815
b11 =
0'
1%
#820
0%
#825
1*
b100 =
b0 9
b1111111000000000000000000000000 #
b1111111000000000000000000000000 .
0;
1%
#830
0%
#835
b110 =
b0 #
b0 .
b0 7
1%
#840
0%
#845
b0 =
1$
1%
#850
0%
#855
0*
b1 =
0$
b11000000000000000000000000 9
b110000000000000000000000 #
b110000000000000000000000 .
b1 7
b110000000000000000000000 &
b110000000000000000000000 (
1'
1%
b10000000100000000000000000000000 ?
b110000000000000000000000 >
#860
0%
#865
b10 =
b11000000000000000000000000 :
0<
b1 8
b10000000100000000000000000000000 &
b10000000100000000000000000000000 (
1%
#870
0%
#875
b11 =
0'
1%
#880
0%
#885
1*
b100000000000000000000000 #
b100000000000000000000000 .
b100 =
b0 9
1%
#890
0%
#895
b110 =
b0 #
b0 .
b0 7
1%
#900
0%
#905
b0 =
1$
1%
